RashlyOutlaid/__init__.py
RashlyOutlaid/api.py
RashlyOutlaid/libwhois.py
RashlyOutlaid/tests.py
RashlyOutlaid-0.15.0.dist-info/LICENSE
RashlyOutlaid-0.15.0.dist-info/METADATA
RashlyOutlaid-0.15.0.dist-info/WHEEL
RashlyOutlaid-0.15.0.dist-info/top_level.txt
RashlyOutlaid-0.15.0.dist-info/RECORD
