Metadata-Version: 2.1
Name: RashlyOutlaid
Version: 0.15.0
Summary: Perform ASN Whois against shadowserver.org
Home-page: https://github.com/bunzen/RashlyOutlaid
Author: Geir Skjotskift
Author-email: geir@underworld.no
License: MIT
Keywords: asn whois shadowserver
Platform: UNKNOWN
Classifier: Development Status :: 4 - Beta
Classifier: Topic :: Utilities
Classifier: License :: OSI Approved :: MIT License
Requires-Python: >=3.6
